urlf/__init__.py
urlf/urlf.py
urlf-2.4.1.dist-info/METADATA
urlf-2.4.1.dist-info/WHEEL
urlf-2.4.1.dist-info/entry_points.txt
urlf-2.4.1.dist-info/top_level.txt
urlf-2.4.1.dist-info/RECORD
