Metadata-Version: 2.4
Name: urlf
Version: 2.4.1
Summary: URL deduplication and normalization tool based on domain and parameter names
Home-page: https://github.com/Boopath1/urlF
Author: 0xBobby
Author-email: rule-entry-0d@icloud.com
Classifier: Programming Language :: Python :: 3
Classifier: License :: OSI Approved :: MIT License
Classifier: Operating System :: OS Independent
Classifier: Environment :: Console
Classifier: Topic :: Internet :: WWW/HTTP
Classifier: Topic :: Utilities
Requires-Python: >=3.6
Requires-Dist: colorlog>=6.0.0
Requires-Dist: tqdm>=4.60.0
Requires-Dist: colorama>=0.4.4
Requires-Dist: pyfiglet>=0.8.post1
Dynamic: author
Dynamic: author-email
Dynamic: classifier
Dynamic: description
Dynamic: description-content-type
Dynamic: home-page
Dynamic: requires-dist
Dynamic: requires-python
Dynamic: summary
